{
    "pearson_correlation_npd": [
        0.8673115948075871, 
        0.8998835413867862
    ], 
    "match_A": [
        157711748, 
        157711748
    ], 
    "fraction of match covered by td injection": [
        0.2582191620884503, 
        0.4133350538724307
    ], 
    "spearman_correlation_npd": [
        0.875745397977703, 
        0.9246175784288307
    ], 
    "spearman_correlation_npv": [
        0.834117218628172, 
        0.9353969879746594
    ], 
    "distance": [
        360.1388621073821, 
        213.7755832643195
    ], 
    "absolute_overlap": [
        5239.6757122587505, 
        7089.033206066093
    ], 
    "absolute_overlap_lg_over_small": [
        7167.653304892222, 
        9395.025288743564
    ], 
    "injection_overlap": [
        0.655749966563627, 
        0.8871986632627541
    ], 
    "source": "PL", 
    "match_B": [
        478376197, 
        263106036
    ], 
    "pearson_correlation_npv": [
        0.6283042818126302, 
        0.8942535563427602
    ]
}